aio4chan.py
aio4chan-0.0.0.dist-info/LICENCE
aio4chan-0.0.0.dist-info/METADATA
aio4chan-0.0.0.dist-info/WHEEL
aio4chan-0.0.0.dist-info/top_level.txt
aio4chan-0.0.0.dist-info/RECORD
