Metadata-Version: 2.1
Name: aio4chan
Version: 0.0.0
Summary: API wrapper for 4chan.
Home-page: https://github.com/Exahilosys/aio4chan
Author: Exahilosys
License: MIT
Download-URL: https://github.com/Exahilosys/aio4chan/archive/v0.0.0.tar.gz
Platform: UNKNOWN
Classifier: License :: OSI Approved :: MIT License
Classifier: Intended Audience :: Developers
Classifier: Natural Language :: English
Classifier: Operating System :: OS Independent
Classifier: Programming Language :: Python :: 3.6
Classifier: Topic :: Internet
Classifier: Topic :: Software Development :: Libraries
Classifier: Topic :: Software Development :: Libraries :: Python Modules
Classifier: Topic :: Utilities
Requires-Dist: aiohttp
